{"AcList":[{"Id":"6","Code":"AF","Name":"Afghanistan","Desc1":"","Desc2":"","Display":"Afghanistan","Type":"Country","Count":0},{"Id":"9","Code":"AL","Name":"Albania","Desc1":"","Desc2":"","Display":"Albania","Type":"Country","Count":0},{"Id":"62","Code":"DZ","Name":"Algeria","Desc1":"","Desc2":"","Display":"Algeria","Type":"Country","Count":0},{"Id":"15","Code":"AS","Name":"American Samoa","Desc1":"","Desc2":"","Display":"American Samoa","Type":"Country","Count":0},{"Id":"4","Code":"AD","Name":"Andorra","Desc1":"","Desc2":"","Display":"Andorra","Type":"Country","Count":0},{"Id":"12","Code":"AO","Name":"Angola","Desc1":"","Desc2":"","Display":"Angola","Type":"Country","Count":0},{"Id":"8","Code":"AI","Name":"Anguilla","Desc1":"","Desc2":"","Display":"Anguilla","Type":"Country","Count":0},{"Id":"13","Code":"AQ","Name":"Antarctica","Desc1":"","Desc2":"","Display":"Antarctica","Type":"Country","Count":0},{"Id":"7","Code":"AG","Name":"Antigua and Barbuda","Desc1":"","Desc2":"","Display":"Antigua and Barbuda","Type":"Country","Count":0},{"Id":"14","Code":"AR","Name":"Argentina","Desc1":"","Desc2":"","Display":"Argentina","Type":"Country","Count":0},{"Id":"10","Code":"AM","Name":"Armenia","Desc1":"","Desc2":"","Display":"Armenia","Type":"Country","Count":0},{"Id":"18","Code":"AW","Name":"Aruba","Desc1":"","Desc2":"","Display":"Aruba","Type":"Country","Count":0},{"Id":"17","Code":"AU","Name":"Australia","Desc1":"","Desc2":"","Display":"Australia","Type":"Country","Count":0},{"Id":"16","Code":"AT","Name":"Austria","Desc1":"","Desc2":"","Display":"Austria","Type":"Country","Count":0},{"Id":"19","Code":"AZ","Name":"Azerbaijan","Desc1":"","Desc2":"","Display":"Azerbaijan","Type":"Country","Count":0},{"Id":"33","Code":"BS","Name":"Bahamas","Desc1":"","Desc2":"","Display":"Bahamas","Type":"Country","Count":0},{"Id":"26","Code":"BH","Name":"Bahrain","Desc1":"","Desc2":"","Display":"Bahrain","Type":"Country","Count":0},{"Id":"22","Code":"BD","Name":"Bangladesh","Desc1":"","Desc2":"","Display":"Bangladesh","Type":"Country","Count":0},{"Id":"21","Code":"BB","Name":"Barbados","Desc1":"","Desc2":"","Display":"Barbados","Type":"Country","Count":0},{"Id":"37","Code":"BY","Name":"Belarus","Desc1":"","Desc2":"","Display":"Belarus","Type":"Country","Count":0},{"Id":"23","Code":"BE","Name":"Belgium","Desc1":"","Desc2":"","Display":"Belgium","Type":"Country","Count":0},{"Id":"38","Code":"BZ","Name":"Belize","Desc1":"","Desc2":"","Display":"Belize","Type":"Country","Count":0},{"Id":"28","Code":"BJ","Name":"Benin","Desc1":"","Desc2":"","Display":"Benin","Type":"Country","Count":0},{"Id":"29","Code":"BM","Name":"Bermuda","Desc1":"","Desc2":"","Display":"Bermuda","Type":"Country","Count":0},{"Id":"34","Code":"BT","Name":"Bhutan","Desc1":"","Desc2":"","Display":"Bhutan","Type":"Country","Count":0},{"Id":"3","Code":"BH","Name":"BHUTAN","Desc1":"","Desc2":"","Display":"BHUTAN","Type":"Country","Count":0},{"Id":"31","Code":"BO","Name":"Bolivia","Desc1":"","Desc2":"","Display":"Bolivia","Type":"Country","Count":0},{"Id":"247","Code":"BQ","Name":"BONAIRE","Desc1":"","Desc2":"","Display":"BONAIRE","Type":"Country","Count":0},{"Id":"20","Code":"BA","Name":"BOSNIA","Desc1":"","Desc2":"","Display":"BOSNIA","Type":"Country","Count":0},{"Id":"36","Code":"BW","Name":"Botswana","Desc1":"","Desc2":"","Display":"Botswana","Type":"Country","Count":0},{"Id":"35","Code":"BV","Name":"Bouvet Island","Desc1":"","Desc2":"","Display":"Bouvet Island","Type":"Country","Count":0},{"Id":"32","Code":"BR","Name":"Brazil","Desc1":"","Desc2":"","Display":"Brazil","Type":"Country","Count":0},{"Id":"105","Code":"IO","Name":"British Indian Ocean Territory","Desc1":"","Desc2":"","Display":"British Indian Ocean Territory","Type":"Country","Count":0},{"Id":"30","Code":"BN","Name":"BRUNEI","Desc1":"","Desc2":"","Display":"BRUNEI","Type":"Country","Count":0},{"Id":"25","Code":"BG","Name":"Bulgaria","Desc1":"","Desc2":"","Display":"Bulgaria","Type":"Country","Count":0},{"Id":"24","Code":"BF","Name":"Burkina Faso","Desc1":"","Desc2":"","Display":"Burkina Faso","Type":"Country","Count":0},{"Id":"27","Code":"BI","Name":"Burundi","Desc1":"","Desc2":"","Display":"Burundi","Type":"Country","Count":0},{"Id":"115","Code":"KH","Name":"Cambodia","Desc1":"","Desc2":"","Display":"Cambodia","Type":"Country","Count":0},{"Id":"47","Code":"CM","Name":"Cameroon","Desc1":"","Desc2":"","Display":"Cameroon","Type":"Country","Count":0},{"Id":"39","Code":"CA","Name":"Canada","Desc1":"","Desc2":"","Display":"Canada","Type":"Country","Count":0},{"Id":"53","Code":"CV","Name":"Cape Verde","Desc1":"","Desc2":"","Display":"Cape Verde","Type":"Country","Count":0},{"Id":"253","Code":"CA","Name":"CARIBBEAN","Desc1":"","Desc2":"","Display":"CARIBBEAN","Type":"Country","Count":0},{"Id":"122","Code":"KY","Name":"Cayman Islands","Desc1":"","Desc2":"","Display":"Cayman Islands","Type":"Country","Count":0},{"Id":"41","Code":"CF","Name":"Central African Republic","Desc1":"","Desc2":"","Display":"Central African Republic","Type":"Country","Count":0},{"Id":"209","Code":"TD","Name":"Chad","Desc1":"","Desc2":"","Display":"Chad","Type":"Country","Count":0},{"Id":"46","Code":"CL","Name":"Chile","Desc1":"","Desc2":"","Display":"Chile","Type":"Country","Count":0},{"Id":"48","Code":"CN","Name":"China","Desc1":"","Desc2":"","Display":"China","Type":"Country","Count":0},{"Id":"54","Code":"CX","Name":"Christmas Island","Desc1":"","Desc2":"","Display":"Christmas Island","Type":"Country","Count":0},{"Id":"40","Code":"CC","Name":"Cocos (Keeling) Islands","Desc1":"","Desc2":"","Display":"Cocos (Keeling) Islands","Type":"Country","Count":0},{"Id":"49","Code":"CO","Name":"Colombia","Desc1":"","Desc2":"","Display":"Colombia","Type":"Country","Count":0},{"Id":"117","Code":"KM","Name":"Comoros","Desc1":"","Desc2":"","Display":"Comoros","Type":"Country","Count":0},{"Id":"45","Code":"CK","Name":"Cook Islands","Desc1":"","Desc2":"","Display":"Cook Islands","Type":"Country","Count":0},{"Id":"50","Code":"CR","Name":"Costa Rica","Desc1":"","Desc2":"","Display":"Costa Rica","Type":"Country","Count":0},{"Id":"259","Code":"CR","Name":"CRIMEA","Desc1":"","Desc2":"","Display":"CRIMEA","Type":"Country","Count":0},{"Id":"98","Code":"HR","Name":"Croatia","Desc1":"","Desc2":"","Display":"Croatia","Type":"Country","Count":0},{"Id":"52","Code":"CU","Name":"Cuba","Desc1":"","Desc2":"","Display":"Cuba","Type":"Country","Count":0},{"Id":"250","Code":"CW","Name":"CURACAO","Desc1":"","Desc2":"","Display":"CURACAO","Type":"Country","Count":0},{"Id":"55","Code":"CY","Name":"Cyprus","Desc1":"","Desc2":"","Display":"Cyprus","Type":"Country","Count":0},{"Id":"56","Code":"CZ","Name":"Czech Republic","Desc1":"","Desc2":"","Display":"Czech Republic","Type":"Country","Count":0},{"Id":"261","Code":"CD","Name":"Democratic Republic of the Congo","Desc1":"","Desc2":"","Display":"Democratic Republic of the Congo","Type":"Country","Count":0},{"Id":"59","Code":"DK","Name":"Denmark","Desc1":"","Desc2":"","Display":"Denmark","Type":"Country","Count":0},{"Id":"58","Code":"DJ","Name":"Djibouti","Desc1":"","Desc2":"","Display":"Djibouti","Type":"Country","Count":0},{"Id":"60","Code":"DM","Name":"Dominica","Desc1":"","Desc2":"","Display":"Dominica","Type":"Country","Count":0},{"Id":"61","Code":"DO","Name":"Dominican Republic","Desc1":"","Desc2":"","Display":"Dominican Republic","Type":"Country","Count":0},{"Id":"218","Code":"TP","Name":"East Timor","Desc1":"","Desc2":"","Display":"East Timor","Type":"Country","Count":0},{"Id":"63","Code":"EC","Name":"Ecuador","Desc1":"","Desc2":"","Display":"Ecuador","Type":"Country","Count":0},{"Id":"65","Code":"EG","Name":"Egypt","Desc1":"","Desc2":"","Display":"Egypt","Type":"Country","Count":0},{"Id":"205","Code":"SV","Name":"El Salvador","Desc1":"","Desc2":"","Display":"El Salvador","Type":"Country","Count":0},{"Id":"88","Code":"GQ","Name":"Equatorial Guinea","Desc1":"","Desc2":"","Display":"Equatorial Guinea","Type":"Country","Count":0},{"Id":"67","Code":"ER","Name":"Eritrea","Desc1":"","Desc2":"","Display":"Eritrea","Type":"Country","Count":0},{"Id":"64","Code":"EE","Name":"Estonia","Desc1":"","Desc2":"","Display":"Estonia","Type":"Country","Count":0},{"Id":"69","Code":"ET","Name":"Ethiopia","Desc1":"","Desc2":"","Display":"Ethiopia","Type":"Country","Count":0},{"Id":"72","Code":"FK","Name":"Falkland Islands","Desc1":"","Desc2":"","Display":"Falkland Islands","Type":"Country","Count":0},{"Id":"74","Code":"FO","Name":"Faroe Islands","Desc1":"","Desc2":"","Display":"Faroe Islands","Type":"Country","Count":0},{"Id":"71","Code":"FJ","Name":"Fiji","Desc1":"","Desc2":"","Display":"Fiji","Type":"Country","Count":0},{"Id":"70","Code":"FI","Name":"Finland","Desc1":"","Desc2":"","Display":"Finland","Type":"Country","Count":0},{"Id":"204","Code":"SU","Name":"Former USSR","Desc1":"","Desc2":"","Display":"Former USSR","Type":"Country","Count":0},{"Id":"75","Code":"FR","Name":"France","Desc1":"","Desc2":"","Display":"France","Type":"Country","Count":0},{"Id":"76","Code":"FX","Name":"France (European Territory)","Desc1":"","Desc2":"","Display":"France (European Territory)","Type":"Country","Count":0},{"Id":"81","Code":"GF","Name":"FRENCH GUIANA","Desc1":"","Desc2":"","Display":"FRENCH GUIANA","Type":"Country","Count":0},{"Id":"172","Code":"PF","Name":"FRENCH POLYNESIA","Desc1":"","Desc2":"","Display":"FRENCH POLYNESIA","Type":"Country","Count":0},{"Id":"210","Code":"TF","Name":"French Southern Territories","Desc1":"","Desc2":"","Display":"French Southern Territories","Type":"Country","Count":0},{"Id":"77","Code":"GA","Name":"Gabon","Desc1":"","Desc2":"","Display":"Gabon","Type":"Country","Count":0},{"Id":"85","Code":"GM","Name":"Gambia","Desc1":"","Desc2":"","Display":"Gambia","Type":"Country","Count":0},{"Id":"80","Code":"GE","Name":"Georgia","Desc1":"","Desc2":"","Display":"Georgia","Type":"Country","Count":0},{"Id":"57","Code":"DE","Name":"Germany","Desc1":"","Desc2":"","Display":"Germany","Type":"Country","Count":0},{"Id":"82","Code":"GH","Name":"Ghana","Desc1":"","Desc2":"","Display":"Ghana","Type":"Country","Count":0},{"Id":"83","Code":"GI","Name":"Gibraltar","Desc1":"","Desc2":"","Display":"Gibraltar","Type":"Country","Count":0},{"Id":"78","Code":"GB","Name":"Great Britain","Desc1":"","Desc2":"","Display":"Great Britain","Type":"Country","Count":0},{"Id":"89","Code":"GR","Name":"Greece","Desc1":"","Desc2":"","Display":"Greece","Type":"Country","Count":0},{"Id":"84","Code":"GL","Name":"Greenland","Desc1":"","Desc2":"","Display":"Greenland","Type":"Country","Count":0},{"Id":"79","Code":"GD","Name":"GRENADA \/CARRICOU","Desc1":"","Desc2":"","Display":"GRENADA \/CARRICOU","Type":"Country","Count":0},{"Id":"87","Code":"GP","Name":"GUADELOUPE","Desc1":"","Desc2":"","Display":"GUADELOUPE","Type":"Country","Count":0},{"Id":"92","Code":"GU","Name":"GUAM","Desc1":"","Desc2":"","Display":"GUAM","Type":"Country","Count":0},{"Id":"91","Code":"GT","Name":"Guatemala","Desc1":"","Desc2":"","Display":"Guatemala","Type":"Country","Count":0},{"Id":"86","Code":"GN","Name":"Guinea","Desc1":"","Desc2":"","Display":"Guinea","Type":"Country","Count":0},{"Id":"93","Code":"GW","Name":"GUINEA-BISSAU","Desc1":"","Desc2":"","Display":"GUINEA-BISSAU","Type":"Country","Count":0},{"Id":"94","Code":"GY","Name":"Guyana","Desc1":"","Desc2":"","Display":"Guyana","Type":"Country","Count":0},{"Id":"99","Code":"HT","Name":"Haiti","Desc1":"","Desc2":"","Display":"Haiti","Type":"Country","Count":0},{"Id":"96","Code":"HM","Name":"Heard and McDonald Islands","Desc1":"","Desc2":"","Display":"Heard and McDonald Islands","Type":"Country","Count":0},{"Id":"97","Code":"HN","Name":"Honduras","Desc1":"","Desc2":"","Display":"Honduras","Type":"Country","Count":0},{"Id":"95","Code":"HK","Name":"Hong Kong","Desc1":"","Desc2":"","Display":"Hong Kong","Type":"Country","Count":0},{"Id":"100","Code":"HU","Name":"Hungary","Desc1":"","Desc2":"","Display":"Hungary","Type":"Country","Count":0},{"Id":"108","Code":"IS","Name":"Iceland","Desc1":"","Desc2":"","Display":"Iceland","Type":"Country","Count":0},{"Id":"104","Code":"IN","Name":"India","Desc1":"+91","Desc2":"bfh-flag-IN","Display":"India","Type":"Country","Count":0},{"Id":"101","Code":"ID","Name":"Indonesia","Desc1":"","Desc2":"","Display":"Indonesia","Type":"Country","Count":0},{"Id":"107","Code":"IR","Name":"Iran","Desc1":"","Desc2":"","Display":"Iran","Type":"Country","Count":0},{"Id":"106","Code":"IQ","Name":"Iraq","Desc1":"","Desc2":"","Display":"Iraq","Type":"Country","Count":0},{"Id":"103","Code":"IL","Name":"Israel","Desc1":"","Desc2":"","Display":"Israel","Type":"Country","Count":0},{"Id":"109","Code":"IT","Name":"Italy","Desc1":"","Desc2":"","Display":"Italy","Type":"Country","Count":0},{"Id":"44","Code":"CI","Name":"IVORY COAST","Desc1":"","Desc2":"","Display":"IVORY COAST","Type":"Country","Count":0},{"Id":"110","Code":"JM","Name":"Jamaica","Desc1":"","Desc2":"","Display":"Jamaica","Type":"Country","Count":0},{"Id":"112","Code":"JP","Name":"Japan","Desc1":"","Desc2":"","Display":"Japan","Type":"Country","Count":0},{"Id":"111","Code":"JO","Name":"Jordan","Desc1":"","Desc2":"","Display":"Jordan","Type":"Country","Count":0},{"Id":"123","Code":"KZ","Name":"Kazakhstan","Desc1":"","Desc2":"","Display":"Kazakhstan","Type":"Country","Count":0},{"Id":"113","Code":"KE","Name":"Kenya","Desc1":"","Desc2":"","Display":"Kenya","Type":"Country","Count":0},{"Id":"116","Code":"KI","Name":"Kiribati","Desc1":"","Desc2":"","Display":"Kiribati","Type":"Country","Count":0},{"Id":"121","Code":"KW","Name":"Kuwait","Desc1":"","Desc2":"","Display":"Kuwait","Type":"Country","Count":0},{"Id":"114","Code":"KG","Name":"Kyrgyzstan","Desc1":"","Desc2":"","Display":"Kyrgyzstan","Type":"Country","Count":0},{"Id":"124","Code":"LA","Name":"Laos","Desc1":"","Desc2":"","Display":"Laos","Type":"Country","Count":0},{"Id":"133","Code":"LV","Name":"Latvia","Desc1":"","Desc2":"","Display":"Latvia","Type":"Country","Count":0},{"Id":"125","Code":"LB","Name":"Lebanon","Desc1":"","Desc2":"","Display":"Lebanon","Type":"Country","Count":0},{"Id":"130","Code":"LS","Name":"Lesotho","Desc1":"","Desc2":"","Display":"Lesotho","Type":"Country","Count":0},{"Id":"129","Code":"LR","Name":"Liberia","Desc1":"","Desc2":"","Display":"Liberia","Type":"Country","Count":0},{"Id":"134","Code":"LY","Name":"Libya","Desc1":"","Desc2":"","Display":"Libya","Type":"Country","Count":0},{"Id":"127","Code":"LI","Name":"Liechtenstein","Desc1":"","Desc2":"","Display":"Liechtenstein","Type":"Country","Count":0},{"Id":"131","Code":"LT","Name":"Lithuania","Desc1":"","Desc2":"","Display":"Lithuania","Type":"Country","Count":0},{"Id":"132","Code":"LU","Name":"Luxembourg","Desc1":"","Desc2":"","Display":"Luxembourg","Type":"Country","Count":0},{"Id":"144","Code":"MO","Name":"Macau","Desc1":"","Desc2":"","Display":"Macau","Type":"Country","Count":0},{"Id":"140","Code":"MK","Name":"Macedonia","Desc1":"","Desc2":"","Display":"Macedonia","Type":"Country","Count":0},{"Id":"138","Code":"MG","Name":"Madagascar","Desc1":"","Desc2":"","Display":"Madagascar","Type":"Country","Count":0},{"Id":"152","Code":"MW","Name":"Malawi","Desc1":"","Desc2":"","Display":"Malawi","Type":"Country","Count":0},{"Id":"154","Code":"MY","Name":"Malaysia","Desc1":"","Desc2":"","Display":"Malaysia","Type":"Country","Count":0},{"Id":"151","Code":"MV","Name":"Maldives","Desc1":"","Desc2":"","Display":"Maldives","Type":"Country","Count":0},{"Id":"141","Code":"ML","Name":"Mali","Desc1":"","Desc2":"","Display":"Mali","Type":"Country","Count":0},{"Id":"149","Code":"MT","Name":"Malta","Desc1":"","Desc2":"","Display":"Malta","Type":"Country","Count":0},{"Id":"139","Code":"MH","Name":"Marshall Islands","Desc1":"","Desc2":"","Display":"Marshall Islands","Type":"Country","Count":0},{"Id":"146","Code":"MQ","Name":"MARTINIQUE","Desc1":"","Desc2":"","Display":"MARTINIQUE","Type":"Country","Count":0},{"Id":"147","Code":"MR","Name":"Mauritania","Desc1":"","Desc2":"","Display":"Mauritania","Type":"Country","Count":0},{"Id":"150","Code":"MU","Name":"Mauritius","Desc1":"","Desc2":"","Display":"Mauritius","Type":"Country","Count":0},{"Id":"241","Code":"YT","Name":"Mayotte","Desc1":"","Desc2":"","Display":"Mayotte","Type":"Country","Count":0},{"Id":"153","Code":"MX","Name":"Mexico","Desc1":"","Desc2":"","Display":"Mexico","Type":"Country","Count":0},{"Id":"73","Code":"FM","Name":"Micronesia","Desc1":"","Desc2":"","Display":"Micronesia","Type":"Country","Count":0},{"Id":"137","Code":"MD","Name":"Moldavia","Desc1":"","Desc2":"","Display":"Moldavia","Type":"Country","Count":0},{"Id":"258","Code":"MO","Name":"MOLDOVA","Desc1":"","Desc2":"","Display":"MOLDOVA","Type":"Country","Count":0},{"Id":"136","Code":"MC","Name":"Monaco","Desc1":"","Desc2":"","Display":"Monaco","Type":"Country","Count":0},{"Id":"143","Code":"MN","Name":"Mongolia","Desc1":"","Desc2":"","Display":"Mongolia","Type":"Country","Count":0},{"Id":"260","Code":"ME","Name":"Montenegro","Desc1":"","Desc2":"","Display":"Montenegro","Type":"Country","Count":0},{"Id":"251","Code":"MO","Name":"MONTENEGRO","Desc1":"","Desc2":"","Display":"MONTENEGRO","Type":"Country","Count":0},{"Id":"148","Code":"MS","Name":"Montserrat","Desc1":"","Desc2":"","Display":"Montserrat","Type":"Country","Count":0},{"Id":"135","Code":"MA","Name":"Morocco","Desc1":"","Desc2":"","Display":"Morocco","Type":"Country","Count":0},{"Id":"155","Code":"MZ","Name":"Mozambique","Desc1":"","Desc2":"","Display":"Mozambique","Type":"Country","Count":0},{"Id":"142","Code":"MM","Name":"MYANMAR-BURMA","Desc1":"","Desc2":"","Display":"MYANMAR-BURMA","Type":"Country","Count":0},{"Id":"156","Code":"NAM","Name":"Namibia","Desc1":"","Desc2":"","Display":"Namibia","Type":"Country","Count":0},{"Id":"165","Code":"NR","Name":"Nauru","Desc1":"","Desc2":"","Display":"Nauru","Type":"Country","Count":0},{"Id":"164","Code":"NP","Name":"Nepal","Desc1":"","Desc2":"","Display":"Nepal","Type":"Country","Count":0},{"Id":"162","Code":"NL","Name":"Netherlands","Desc1":"","Desc2":"","Display":"Netherlands","Type":"Country","Count":0},{"Id":"11","Code":"AN","Name":"Netherlands Antilles","Desc1":"","Desc2":"","Display":"Netherlands Antilles","Type":"Country","Count":0},{"Id":"166","Code":"NT","Name":"Neutral Zone","Desc1":"","Desc2":"","Display":"Neutral Zone","Type":"Country","Count":0},{"Id":"157","Code":"NC","Name":"NEW CALEDONIA","Desc1":"","Desc2":"","Display":"NEW CALEDONIA","Type":"Country","Count":0},{"Id":"168","Code":"NZ","Name":"New Zealand","Desc1":"","Desc2":"","Display":"New Zealand","Type":"Country","Count":0},{"Id":"161","Code":"NI","Name":"Nicaragua","Desc1":"","Desc2":"","Display":"Nicaragua","Type":"Country","Count":0},{"Id":"158","Code":"NE","Name":"Niger","Desc1":"","Desc2":"","Display":"Niger","Type":"Country","Count":0},{"Id":"160","Code":"NG","Name":"Nigeria","Desc1":"","Desc2":"","Display":"Nigeria","Type":"Country","Count":0},{"Id":"167","Code":"NU","Name":"Niue","Desc1":"","Desc2":"","Display":"Niue","Type":"Country","Count":0},{"Id":"159","Code":"NF","Name":"Norfolk Island","Desc1":"","Desc2":"","Display":"Norfolk Island","Type":"Country","Count":0},{"Id":"119","Code":"KP","Name":"North Korea","Desc1":"","Desc2":"","Display":"North Korea","Type":"Country","Count":0},{"Id":"145","Code":"MP","Name":"Northern Mariana Islands","Desc1":"","Desc2":"","Display":"Northern Mariana Islands","Type":"Country","Count":0},{"Id":"163","Code":"NO","Name":"Norway","Desc1":"","Desc2":"","Display":"Norway","Type":"Country","Count":0},{"Id":"0","Code":"NA","Name":"Not Assigned","Desc1":"","Desc2":"","Display":"Not Assigned","Type":"Country","Count":0},{"Id":"169","Code":"OM","Name":"Oman","Desc1":"","Desc2":"","Display":"Oman","Type":"Country","Count":0},{"Id":"175","Code":"PK","Name":"Pakistan","Desc1":"","Desc2":"","Display":"Pakistan","Type":"Country","Count":0},{"Id":"255","Code":"PS","Name":"PALESTINIAN TERRITORY","Desc1":"","Desc2":"","Display":"PALESTINIAN TERRITORY","Type":"Country","Count":0},{"Id":"170","Code":"PA","Name":"Panama","Desc1":"","Desc2":"","Display":"Panama","Type":"Country","Count":0},{"Id":"173","Code":"PG","Name":"Papua New Guinea","Desc1":"","Desc2":"","Display":"Papua New Guinea","Type":"Country","Count":0},{"Id":"182","Code":"PY","Name":"Paraguay","Desc1":"","Desc2":"","Display":"Paraguay","Type":"Country","Count":0},{"Id":"171","Code":"PE","Name":"Peru","Desc1":"","Desc2":"","Display":"Peru","Type":"Country","Count":0},{"Id":"264","Code":"PER","Name":"Peru","Desc1":"","Desc2":"","Display":"Peru","Type":"Country","Count":0},{"Id":"174","Code":"PH","Name":"Philippines","Desc1":"","Desc2":"","Display":"Philippines","Type":"Country","Count":0},{"Id":"178","Code":"PN","Name":"Pitcairn Island","Desc1":"","Desc2":"","Display":"Pitcairn Island","Type":"Country","Count":0},{"Id":"176","Code":"PL","Name":"Poland","Desc1":"","Desc2":"","Display":"Poland","Type":"Country","Count":0},{"Id":"180","Code":"PT","Name":"Portugal","Desc1":"","Desc2":"","Display":"Portugal","Type":"Country","Count":0},{"Id":"179","Code":"PR","Name":"Puerto Rico","Desc1":"","Desc2":"","Display":"Puerto Rico","Type":"Country","Count":0},{"Id":"183","Code":"QA","Name":"Qatar","Desc1":"","Desc2":"","Display":"Qatar","Type":"Country","Count":0},{"Id":"42","Code":"CG","Name":"REPUBLIC OF CONGO","Desc1":"","Desc2":"","Display":"REPUBLIC OF CONGO","Type":"Country","Count":0},{"Id":"102","Code":"IE","Name":"REPUBLIC OF IRELAND","Desc1":"","Desc2":"","Display":"REPUBLIC OF IRELAND","Type":"Country","Count":0},{"Id":"181","Code":"PW","Name":"REPUBLIC OF PALAU","Desc1":"","Desc2":"","Display":"REPUBLIC OF PALAU","Type":"Country","Count":0},{"Id":"184","Code":"RE","Name":"REUNION","Desc1":"","Desc2":"","Display":"REUNION","Type":"Country","Count":0},{"Id":"185","Code":"RO","Name":"Romania","Desc1":"","Desc2":"","Display":"Romania","Type":"Country","Count":0},{"Id":"186","Code":"RU","Name":"RUSSIA","Desc1":"","Desc2":"","Display":"RUSSIA","Type":"Country","Count":0},{"Id":"187","Code":"RW","Name":"Rwanda","Desc1":"","Desc2":"","Display":"Rwanda","Type":"Country","Count":0},{"Id":"90","Code":"GS","Name":"S. Georgia & S. Sandwich Isls.","Desc1":"","Desc2":"","Display":"S. Georgia & S. Sandwich Isls.","Type":"Country","Count":0},{"Id":"248","Code":"BL","Name":"SAINT BARTHELEMY","Desc1":"","Desc2":"","Display":"SAINT BARTHELEMY","Type":"Country","Count":0},{"Id":"194","Code":"SH","Name":"Saint Helena","Desc1":"","Desc2":"","Display":"Saint Helena","Type":"Country","Count":0},{"Id":"118","Code":"KN","Name":"SAINT KITTS AND NEVIS","Desc1":"","Desc2":"","Display":"SAINT KITTS AND NEVIS","Type":"Country","Count":0},{"Id":"249","Code":"MF","Name":"SAINT MARTIN (FRENCH PART)","Desc1":"","Desc2":"","Display":"SAINT MARTIN (FRENCH PART)","Type":"Country","Count":0},{"Id":"177","Code":"PM","Name":"Saint Pierre and Miquelon","Desc1":"","Desc2":"","Display":"Saint Pierre and Miquelon","Type":"Country","Count":0},{"Id":"232","Code":"VC","Name":"SAINT VINCENT AND THE GRENADINES","Desc1":"","Desc2":"","Display":"SAINT VINCENT AND THE GRENADINES","Type":"Country","Count":0},{"Id":"239","Code":"WS","Name":"Samoa","Desc1":"","Desc2":"","Display":"Samoa","Type":"Country","Count":0},{"Id":"199","Code":"SM","Name":"San Marino","Desc1":"","Desc2":"","Display":"San Marino","Type":"Country","Count":0},{"Id":"203","Code":"ST","Name":"SAO TOME AND PRINCIPE","Desc1":"","Desc2":"","Display":"SAO TOME AND PRINCIPE","Type":"Country","Count":0},{"Id":"188","Code":"SA","Name":"Saudi Arabia","Desc1":"","Desc2":"","Display":"Saudi Arabia","Type":"Country","Count":0},{"Id":"200","Code":"SN","Name":"Senegal","Desc1":"","Desc2":"","Display":"Senegal","Type":"Country","Count":0},{"Id":"254","Code":"RS","Name":"SERBIA","Desc1":"","Desc2":"","Display":"SERBIA","Type":"Country","Count":0},{"Id":"190","Code":"SC","Name":"Seychelles","Desc1":"","Desc2":"","Display":"Seychelles","Type":"Country","Count":0},{"Id":"198","Code":"SL","Name":"Sierra Leone","Desc1":"","Desc2":"","Display":"Sierra Leone","Type":"Country","Count":0},{"Id":"193","Code":"SG","Name":"Singapore","Desc1":"","Desc2":"","Display":"Singapore","Type":"Country","Count":0},{"Id":"257","Code":"SX","Name":"SINT MAARTEN (DUTCH PART)","Desc1":"","Desc2":"","Display":"SINT MAARTEN (DUTCH PART)","Type":"Country","Count":0},{"Id":"197","Code":"SK","Name":"Slovak Republic","Desc1":"","Desc2":"","Display":"Slovak Republic","Type":"Country","Count":0},{"Id":"51","Code":"CS","Name":"SLOVAKIA","Desc1":"","Desc2":"","Display":"SLOVAKIA","Type":"Country","Count":0},{"Id":"195","Code":"SI","Name":"Slovenia","Desc1":"","Desc2":"","Display":"Slovenia","Type":"Country","Count":0},{"Id":"189","Code":"SB","Name":"Solomon Islands","Desc1":"","Desc2":"","Display":"Solomon Islands","Type":"Country","Count":0},{"Id":"201","Code":"SO","Name":"Somalia","Desc1":"","Desc2":"","Display":"Somalia","Type":"Country","Count":0},{"Id":"243","Code":"ZA","Name":"South Africa","Desc1":"","Desc2":"","Display":"South Africa","Type":"Country","Count":0},{"Id":"120","Code":"KR","Name":"South Korea","Desc1":"","Desc2":"","Display":"South Korea","Type":"Country","Count":0},{"Id":"68","Code":"ES","Name":"Spain","Desc1":"","Desc2":"","Display":"Spain","Type":"Country","Count":0},{"Id":"128","Code":"LK","Name":"Sri Lanka","Desc1":"","Desc2":"","Display":"Sri Lanka","Type":"Country","Count":0},{"Id":"126","Code":"LC","Name":"ST LUCIA","Desc1":"","Desc2":"","Display":"ST LUCIA","Type":"Country","Count":0},{"Id":"191","Code":"SD","Name":"Sudan","Desc1":"","Desc2":"","Display":"Sudan","Type":"Country","Count":0},{"Id":"202","Code":"SR","Name":"Suriname","Desc1":"","Desc2":"","Display":"Suriname","Type":"Country","Count":0},{"Id":"196","Code":"SJ","Name":"Svalbard and Jan Mayen Islands","Desc1":"","Desc2":"","Display":"Svalbard and Jan Mayen Islands","Type":"Country","Count":0},{"Id":"207","Code":"SZ","Name":"Swaziland","Desc1":"","Desc2":"","Display":"Swaziland","Type":"Country","Count":0},{"Id":"192","Code":"SE","Name":"Sweden","Desc1":"","Desc2":"","Display":"Sweden","Type":"Country","Count":0},{"Id":"43","Code":"CH","Name":"Switzerland","Desc1":"","Desc2":"","Display":"Switzerland","Type":"Country","Count":0},{"Id":"206","Code":"SY","Name":"Syria","Desc1":"","Desc2":"","Display":"Syria","Type":"Country","Count":0},{"Id":"222","Code":"TW","Name":"Taiwan","Desc1":"","Desc2":"","Display":"Taiwan","Type":"Country","Count":0},{"Id":"213","Code":"TJ","Name":"TAJIKISTAN","Desc1":"","Desc2":"","Display":"TAJIKISTAN","Type":"Country","Count":0},{"Id":"223","Code":"TZ","Name":"Tanzania","Desc1":"","Desc2":"","Display":"Tanzania","Type":"Country","Count":0},{"Id":"212","Code":"TH","Name":"Thailand","Desc1":"","Desc2":"","Display":"Thailand","Type":"Country","Count":0},{"Id":"211","Code":"TG","Name":"Togo","Desc1":"","Desc2":"","Display":"Togo","Type":"Country","Count":0},{"Id":"214","Code":"TK","Name":"Tokelau","Desc1":"","Desc2":"","Display":"Tokelau","Type":"Country","Count":0},{"Id":"217","Code":"TO","Name":"Tonga","Desc1":"","Desc2":"","Display":"Tonga","Type":"Country","Count":0},{"Id":"220","Code":"TT","Name":"Trinidad and Tobago","Desc1":"","Desc2":"","Display":"Trinidad and Tobago","Type":"Country","Count":0},{"Id":"216","Code":"TN","Name":"Tunisia","Desc1":"","Desc2":"","Display":"Tunisia","Type":"Country","Count":0},{"Id":"219","Code":"TR","Name":"Turkey","Desc1":"","Desc2":"","Display":"Turkey","Type":"Country","Count":0},{"Id":"215","Code":"TM","Name":"Turkmenistan","Desc1":"","Desc2":"","Display":"Turkmenistan","Type":"Country","Count":0},{"Id":"208","Code":"TC","Name":"TURKS \/ CAICOS","Desc1":"","Desc2":"","Display":"TURKS \/ CAICOS","Type":"Country","Count":0},{"Id":"221","Code":"TV","Name":"Tuvalu","Desc1":"","Desc2":"","Display":"Tuvalu","Type":"Country","Count":0},{"Id":"235","Code":"VI","Name":"U.S. VIRGIN ISLANDS","Desc1":"","Desc2":"","Display":"U.S. VIRGIN ISLANDS","Type":"Country","Count":0},{"Id":"225","Code":"UG","Name":"Uganda","Desc1":"","Desc2":"","Display":"Uganda","Type":"Country","Count":0},{"Id":"224","Code":"UA","Name":"Ukraine","Desc1":"","Desc2":"","Display":"Ukraine","Type":"Country","Count":0},{"Id":"5","Code":"AE","Name":"United Arab Emirates","Desc1":"+971","Desc2":"bfh-flag-AE","Display":"United Arab Emirates","Type":"Country","Count":0},{"Id":"226","Code":"UK","Name":"United Kingdom","Desc1":"","Desc2":"","Display":"United Kingdom","Type":"Country","Count":0},{"Id":"228","Code":"US","Name":"UNITED STATES OF AMERICA","Desc1":"","Desc2":"","Display":"UNITED STATES OF AMERICA","Type":"Country","Count":0},{"Id":"229","Code":"UY","Name":"Uruguay","Desc1":"","Desc2":"","Display":"Uruguay","Type":"Country","Count":0},{"Id":"227","Code":"UM","Name":"USA Minor Outlying Islands","Desc1":"","Desc2":"","Display":"USA Minor Outlying Islands","Type":"Country","Count":0},{"Id":"230","Code":"UZ","Name":"Uzbekistan","Desc1":"","Desc2":"","Display":"Uzbekistan","Type":"Country","Count":0},{"Id":"237","Code":"VU","Name":"Vanuatu","Desc1":"","Desc2":"","Display":"Vanuatu","Type":"Country","Count":0},{"Id":"231","Code":"VA","Name":"Vatican City State","Desc1":"","Desc2":"","Display":"Vatican City State","Type":"Country","Count":0},{"Id":"233","Code":"VE","Name":"Venezuela","Desc1":"","Desc2":"","Display":"Venezuela","Type":"Country","Count":0},{"Id":"236","Code":"VN","Name":"Vietnam","Desc1":"","Desc2":"","Display":"Vietnam","Type":"Country","Count":0},{"Id":"234","Code":"VG","Name":"Virgin Islands (British)","Desc1":"","Desc2":"","Display":"Virgin Islands (British)","Type":"Country","Count":0},{"Id":"238","Code":"WF","Name":"Wallis and Futuna Islands","Desc1":"","Desc2":"","Display":"Wallis and Futuna Islands","Type":"Country","Count":0},{"Id":"252","Code":"WB","Name":"WEST BANK","Desc1":"","Desc2":"","Display":"WEST BANK","Type":"Country","Count":0},{"Id":"66","Code":"EH","Name":"Western Sahara","Desc1":"","Desc2":"","Display":"Western Sahara","Type":"Country","Count":0},{"Id":"240","Code":"YE","Name":"Yemen","Desc1":"","Desc2":"","Display":"Yemen","Type":"Country","Count":0},{"Id":"242","Code":"YU","Name":"Yugoslavia","Desc1":"","Desc2":"","Display":"Yugoslavia","Type":"Country","Count":0},{"Id":"245","Code":"ZR","Name":"Zaire","Desc1":"","Desc2":"","Display":"Zaire","Type":"Country","Count":0},{"Id":"244","Code":"ZM","Name":"Zambia","Desc1":"","Desc2":"","Display":"Zambia","Type":"Country","Count":0},{"Id":"256","Code":"ZW","Name":"ZIMBABWE","Desc1":"","Desc2":"","Display":"ZIMBABWE","Type":"Country","Count":0}],"Authenticated":"True","SessionId":"a53c23f599c442d2b81731d87c297f70","LogReferenceId":"a53c23f599c442d2b81731d87c297f70","ClientCode":"SWETRI00","EntityId":10,"ClientId":"17777","LanguageLocale":"en-US","StatusType":"Success","StatusCode":"S0001","StatusMessage":"Operation Was Successful"}